{
    "zer0shiki": {
        "team_rating": 2316,
        "members": [
            "<span class=\"user-yellow\">zer0star</span>",
            "<span class=\"user-yellow\">kenken714</span>",
            "<span class=\"user-blue\">Comavius</span>"
        ]
    },
    "Tsukuyom1": {
        "team_rating": 1936,
        "members": [
            "<span class=\"user-blue\">ZOIZOI</span>",
            "<span class=\"user-blue\">jupiter_68</span>",
            "<span class=\"user-cyan\">Oxojo</span>"
        ]
    },
    "ACORN": {
        "team_rating": 2377,
        "members": [
            "<span class=\"user-yellow\">Astral__</span>",
            "<span class=\"user-yellow\">cho57020</span>",
            "<span class=\"user-yellow\">otoshigo</span>"
        ]
    },
    "AMATSUKAZE": {
        "team_rating": 2801,
        "members": [
            "<span class=\"user-orange\">noya2</span>",
            "<span class=\"user-orange\">shobonvip</span>",
            "<span class=\"user-orange\">Rice_tawara459</span>"
        ]
    },
    "DaiMonge": {
        "team_rating": 2774,
        "members": [
            "<span class=\"user-yellow\">TKO</span>",
            "<span class=\"user-orange\">yuma220284</span>",
            "<span class=\"user-orange\">KumaTachiRen</span>"
        ]
    },
    "bogosort": {
        "team_rating": 2484,
        "members": [
            "<span class=\"user-orange\">soryuusi0219</span>",
            "<span class=\"user-blue\">jastaway</span>",
            "<span class=\"user-cyan\">tatesoto</span>"
        ]
    },
    "The Revenge of shinchan": {
        "team_rating": 3144,
        "members": [
            "<span><img src=\"https://img.atcoder.jp/assets/icon/crown_bronze.png\"/><span class=\"user-red\">Nachia</span></span>",
            "<span class=\"user-yellow\">KowerKoint</span>",
            "<span class=\"user-yellow\">krit3379</span>"
        ]
    },
    "HAOU KAYAMA": {
        "team_rating": 2209,
        "members": [
            "Sotatsu",
            "<span class=\"user-yellow\">Nzt3</span>",
            "<span class=\"user-blue\">Koi51</span>"
        ]
    },
    "o3-kayama": {
        "team_rating": 2716,
        "members": [
            "<span class=\"user-orange\">ponjuice</span>",
            "<span class=\"user-orange\">Series_205</span>",
            "<span class=\"user-yellow\">hir35</span>"
        ]
    },
    "KingNU": {
        "team_rating": 2304,
        "members": [
            "<span class=\"user-yellow\">mono_1729</span>",
            "<span class=\"user-yellow\">hirakuuuu</span>",
            "<span class=\"user-blue\">US_cube</span>"
        ]
    },
    "NUcomer": {
        "team_rating": 2145,
        "members": [
            "<span class=\"user-blue\">tour2st</span>",
            "<span class=\"user-blue\">Levixi</span>",
            "<span class=\"user-blue\">Jinapetto</span>"
        ]
    },
    "c..OwO..2": {
        "team_rating": 2296,
        "members": [
            "<span class=\"user-yellow\">FUN_Morikubo</span>",
            "<span class=\"user-cyan\">wisteriahuman</span>",
            "<span class=\"user-unrated\">mochi</span>"
        ]
    },
    "Informatical_KU_B-tree": {
        "team_rating": 2210,
        "members": [
            "<span class=\"user-yellow\">m1une</span>",
            "<span class=\"user-blue\">miie</span>",
            "<span class=\"user-cyan\">pentaproton</span>"
        ]
    },
    "Maximum Masters": {
        "team_rating": 1927,
        "members": [
            "<span class=\"user-blue\">a01sa01to</span>",
            "<span class=\"user-blue\">through</span>",
            "<span class=\"user-green\">kAsA02</span>"
        ]
    },
    "The Revenge of take000": {
        "team_rating": 1929,
        "members": [
            "<span class=\"user-blue\">shogo314</span>",
            "<span class=\"user-green\">Taniquchi</span>",
            "<span class=\"user-gray\">himi_Hi</span>"
        ]
    },
    "K1NTOKI": {
        "team_rating": 2165,
        "members": [
            "<span class=\"user-blue\">k1suxu</span>",
            "<span class=\"user-blue\">toku4388</span>",
            "<span class=\"user-cyan\">kyomikyomi</span>"
        ]
    },
    "CT-_-RL": {
        "team_rating": 1746,
        "members": [
            "<span class=\"user-blue\">miztom</span>",
            "<span class=\"user-brown\">OkaKiyoshi</span>",
            "<span class=\"user-gray\">yunakonabanana</span>"
        ]
    },
    "1.5Nachia": {
        "team_rating": 2171,
        "members": [
            "<span class=\"user-yellow\">hiro71687</span>",
            "<span class=\"user-blue\">besukohu</span>",
            "<span class=\"user-cyan\">Herring101</span>"
        ]
    },
    "Aobayama_Marines": {
        "team_rating": 2385,
        "members": [
            "<span class=\"user-yellow\">suo</span>",
            "<span class=\"user-blue\">E49869826</span>",
            "<span class=\"user-blue\">tanaka2_55</span>"
        ]
    },
    "AtKober": {
        "team_rating": 1869,
        "members": [
            "<span class=\"user-blue\">tmb</span>",
            "<span class=\"user-cyan\">fky_</span>",
            "<span class=\"user-green\">poisonkumaa</span>"
        ]
    },
    "Syntax Sugar": {
        "team_rating": 1801,
        "members": [
            "<span class=\"user-blue\">haruki4936</span>",
            "<span class=\"user-cyan\">Kei83</span>",
            "<span class=\"user-cyan\">ja14378</span>"
        ]
    },
    "Rinshan Solution": {
        "team_rating": 3036,
        "members": [
            "<span><img src=\"https://img.atcoder.jp/assets/icon/crown_bronze.png\"/><span class=\"user-red\">PCTprobability</span></span>",
            "<span class=\"user-yellow\">harurun4635</span>",
            "<span class=\"user-yellow\">kemuniku</span>"
        ]
    },
    "StackQverflow": {
        "team_rating": 1880,
        "members": [
            "<span class=\"user-blue\">autumn09</span>",
            "<span class=\"user-blue\">downer</span>",
            "<span class=\"user-green\">tossy2002</span>"
        ]
    },
    "NUionfind": {
        "team_rating": 1512,
        "members": [
            "<span class=\"user-cyan\">powell</span>",
            "<span class=\"user-cyan\">mattsunkun</span>",
            "<span class=\"user-green\">hamao</span>"
        ]
    },
    "Dynamic_Soroban": {
        "team_rating": 1646,
        "members": [
            "<span class=\"user-cyan\">hayatroid</span>",
            "neshin",
            "<span class=\"user-cyan\">N_noa21</span>"
        ]
    },
    "neko kick nyaaa-": {
        "team_rating": 1741,
        "members": [
            "<span class=\"user-blue\">uruzunyaa</span>",
            "<span class=\"user-green\">HackberryA3</span>",
            "<span class=\"user-brown\">Orca1122</span>"
        ]
    },
    "KBM": {
        "team_rating": 1568,
        "members": [
            "<span class=\"user-cyan\">ma_tw</span>",
            "<span class=\"user-cyan\">yurina256</span>",
            "<span class=\"user-green\">llMotoll</span>"
        ]
    },
    "Sophia Pythonista": {
        "team_rating": 1938,
        "members": [
            "<span class=\"user-blue\">nikoro256</span>",
            "<span class=\"user-cyan\">Suzux</span>",
            "<span class=\"user-green\">trkwm</span>"
        ]
    },
    "corbeau": {
        "team_rating": 2016,
        "members": [
            "<span class=\"user-yellow\">Kyo_s_s</span>",
            "Ackvy",
            "<span class=\"user-brown\">Binomial</span>"
        ]
    },
    "Aobayama_BlueMountain": {
        "team_rating": 2201,
        "members": [
            "<span class=\"user-blue\">ripity</span>",
            "<span class=\"user-yellow\">n_o_n_o_n</span>",
            "<span class=\"user-green\">aqua_dhmo</span>"
        ]
    },
    "edakari_ha_iyada": {
        "team_rating": 1668,
        "members": [
            "<span class=\"user-cyan\">ramdos</span>",
            "<span class=\"user-cyan\">TwoSquirrels</span>",
            "<span class=\"user-cyan\">ryu150</span>"
        ]
    },
    "Magical Fish": {
        "team_rating": 2471,
        "members": [
            "<span class=\"user-yellow\">confeito</span>",
            "<span class=\"user-yellow\">serendipity_</span>",
            "<span class=\"user-yellow\">miscalculation53</span>"
        ]
    },
    "y_1": {
        "team_rating": 2281,
        "members": [
            "<span class=\"user-blue\">kouty</span>",
            "<span class=\"user-yellow\">hato_</span>",
            "<span class=\"user-blue\">ococonomy1</span>"
        ]
    },
    "homework": {
        "team_rating": 1982,
        "members": [
            "<span class=\"user-blue\">houren</span>",
            "<span class=\"user-green\">memin</span>",
            "<span class=\"user-green\">woody_1227</span>"
        ]
    },
    "midoribeko": {
        "team_rating": 1391,
        "members": [
            "<span class=\"user-green\">sorachandu</span>",
            "<span class=\"user-green\">hotate29</span>",
            "<span class=\"user-green\">taio</span>"
        ]
    },
    "rikoriko": {
        "team_rating": 1520,
        "members": [
            "\u305f\u304d\u306a",
            "<span class=\"user-cyan\">h1rano</span>",
            "[@haruharu_RQA&gt;twitter:\u306f\u308b\u306f\u308b]"
        ]
    },
    "knowcow": {
        "team_rating": 2098,
        "members": [
            "<span class=\"user-blue\">kobaryo222</span>",
            "<span class=\"user-green\">sunrize</span>",
            "<span class=\"user-yellow\">lX57</span>"
        ]
    },
    "Chu-San-Gen": {
        "team_rating": 1599,
        "members": [
            "Yutch591",
            "<span class=\"user-cyan\">Shizuki55</span>",
            "<span class=\"user-cyan\">pop_o</span>"
        ]
    },
    "BZS": {
        "team_rating": 918,
        "members": [
            "<span class=\"user-brown\">sen469</span>",
            "<span class=\"user-brown\">Tehom</span>",
            "\u3042\u305a\u3073\u308f"
        ]
    },
    "GU": {
        "team_rating": 2103,
        "members": [
            "<span class=\"user-unrated\">Shian</span>",
            "MS",
            "<span class=\"user-yellow\">akua</span>"
        ]
    },
    "password1234": {
        "team_rating": 969,
        "members": [
            "<span class=\"user-brown\">nakakouTV</span>",
            "<span class=\"user-green\">hakakeen</span>",
            "<span class=\"user-gray\">KomeijiArmia</span>"
        ]
    }
}